bookied/config.py
bookied/__init__.py
bookied/redis_con.py
bookied/cli.py
bookied/endpointschema.py
bookied/web.py
bookied/work.py
bookied-0.0.3.dist-info/entry_points.txt
bookied-0.0.3.dist-info/top_level.txt
bookied-0.0.3.dist-info/METADATA
bookied-0.0.3.dist-info/DESCRIPTION.rst
bookied-0.0.3.dist-info/metadata.json
bookied-0.0.3.dist-info/WHEEL
bookied-0.0.3.dist-info/RECORD
