Metadata-Version: 2.0
Name: bookied
Version: 0.0.3
Summary: A daemon to manage synchronization with the blockchain
Home-page: http://pbsa.info
Author: Fabian Schuh
Author-email: Fabian.Schuh@BlockchainProjectsBV.com
Maintainer: Fabian Schuh
Maintainer-email: Fabian.Schuh@BlockchainProjectsBV.com
License: UNKNOWN
Download-URL: https://github.com/pbsa/bookied/tarball/0.0.3
Keywords: peerplays,bookied
Platform: UNKNOWN
Classifier: License :: OSI Approved :: MIT License
Classifier: Operating System :: OS Independent
Classifier: Programming Language :: Python :: 3
Classifier: Development Status :: 3 - Alpha
Classifier: Intended Audience :: Developers
Requires-Dist: peerplays
Requires-Dist: prettytable
Requires-Dist: click
Requires-Dist: jsonschema
Requires-Dist: pyyaml
Requires-Dist: flask
Requires-Dist: redis
Requires-Dist: flask-rq
Requires-Dist: dateutils
Requires-Dist: bookiesports
Requires-Dist: bookied-sync
